vulzap/__init__.py
vulzap/database.py
vulzap/main.py
vulzap/settings.py
vulzap/utils.py
vulzap/core/__init__.py
vulzap/core/analyzer.py
vulzap/core/crawl.py
vulzap/core/hud.py
vulzap/core/proxy.py
vulzap/db/__init__.py
vulzap/db/models.py
vulzap/db/sql.py
vulzap/plugins/__init__.py
vulzap/plugins/sqli.py
vulzap/plugins/xss.py
vulzap/web/__init__.py
vulzap/web/app.py
vulzap/web/static/interaction.css
vulzap/web/static/mainstyle.css
vulzap/web/static/substyle.css
vulzap/web/templates/index.html
vulzap/web/templates/interaction.html
vulzap/web/templates/output.html
vulzap-0.1.1.dist-info/LICENSE
vulzap-0.1.1.dist-info/METADATA
vulzap-0.1.1.dist-info/WHEEL
vulzap-0.1.1.dist-info/entry_points.txt
vulzap-0.1.1.dist-info/top_level.txt
vulzap-0.1.1.dist-info/RECORD
