Metadata-Version: 2.1
Name: vulzap
Version: 0.1.1
Summary: 0/1-Day Semiautomation Anaylsis Tool
Author: vulzap
Author-email: gandy297@gmail.com
License: MIT
Classifier: License :: OSI Approved :: MIT License
Classifier: Programming Language :: Python :: 3 :: Only
Classifier: Operating System :: OS Independent
Requires-Python: >=3.8
License-File: LICENSE
Requires-Dist: beautifulsoup4
Requires-Dist: requests
Requires-Dist: Flask
Requires-Dist: mitmproxy
Requires-Dist: mysql
Requires-Dist: mysqlclient
Requires-Dist: python-dotenv
Requires-Dist: termcolor
Requires-Dist: urllib3
Requires-Dist: selenium
Requires-Dist: lxml
